mongo_drf_endpoint_logger/__init__.py
mongo_drf_endpoint_logger/helpers.py
mongo_drf_endpoint_logger/models.py
mongo_drf_endpoint_logger/operations.py
mongo_drf_endpoint_logger/serializers.py
mongo_drf_endpoint_logger/tests.py
mongo_drf_endpoint_logger/threads.py
mongo_drf_endpoint_logger/utils.py
mongo_drf_endpoint_logger/middleware/__init__.py
mongo_drf_endpoint_logger/middleware/endpoint_logger_middleware.py
mongo_drf_endpoint_logger-0.1.9.dist-info/LICENSE
mongo_drf_endpoint_logger-0.1.9.dist-info/METADATA
mongo_drf_endpoint_logger-0.1.9.dist-info/WHEEL
mongo_drf_endpoint_logger-0.1.9.dist-info/top_level.txt
mongo_drf_endpoint_logger-0.1.9.dist-info/RECORD
