Metadata-Version: 2.1
Name: mongo-drf-endpoint-logger
Version: 0.1.9
Summary: An API Logger for your Django Rest Framework project with Mongo DB.
Home-page: https://github.com/inanpy/mongo_drf_endpoint_logger
Author: Inan Delibas
Author-email: inanndelibas@gmail.com
License: MIT
Classifier: Programming Language :: Python :: 3
Classifier: License :: OSI Approved :: MIT License
Classifier: Operating System :: OS Independent
Requires-Python: >=3.6
License-File: LICENSE
Requires-Dist: Django (>=3.0.0djangorestframework>=3.0.0mongoengine>=0.24.1)
